calculate/__init__.py
calculate/calc.py
calculate/unit_test.py
example_pkg_pavelg48-1.1.data/scripts/calc.py
example_pkg_pavelg48-1.1.dist-info/METADATA
example_pkg_pavelg48-1.1.dist-info/WHEEL
example_pkg_pavelg48-1.1.dist-info/top_level.txt
example_pkg_pavelg48-1.1.dist-info/RECORD
