Metadata-Version: 2.1
Name: example-pkg-pavelg48
Version: 1.1
Summary: A first small example package
Home-page: https://github.com/naturalett/getting-started
Author: JerLion
Author-email: pavelg48@example.com
License: UNKNOWN
Platform: UNKNOWN
Requires-Python: >=3.9
